excel2x/.DS_Store
excel2x/__init__.py
excel2x/_version.py
excel2x/config_template.json
excel2x/core.py
excel2x/excel_reader.py
excel2x/excel_writer.py
excel2x/main.py
excel2x/utils.py
excel2x/formats/.DS_Store
excel2x/formats/__init__.py
excel2x/formats/formatter.py
excel2x/formats/json_fmt.py
excel2x/formats/lua_fmt.py
excel2x-0.0.6.dist-info/METADATA
excel2x-0.0.6.dist-info/WHEEL
excel2x-0.0.6.dist-info/entry_points.txt
excel2x-0.0.6.dist-info/RECORD
