Metadata-Version: 2.1
Name: excel2x
Version: 0.0.6
Summary: A excel convert package
Project-URL: Bug Tracker, https://github.com/
Project-URL: Homepage, https://github.com/
Author-email: Fan <fan@example.com>
Classifier: License :: OSI Approved :: MIT License
Classifier: Operating System :: OS Independent
Classifier: Programming Language :: Python :: 3
Requires-Python: >=3.8
Requires-Dist: openpyxl
